{
  "Children": [
    {
      "Children": [],
      "BlockType": "$RSI",
      "Unknown0C": 0,
      "Data": {
        "BaseBuffer": {
          "type": "Buffer",
          "data": [
            6,
            5,
            4,
            2,
            0,
            0,
            0,
            0,
            0,
            0,
            0,
            0,
            48,
            0,
            0,
            0,
            192,
            233,
            5,
            32,
            160,
            25,
            1,
            0,
            16,
            0,
            0,
            0,
            0,
            0,
            0,
            0,
            96,
            3,
            7,
            32,
            52,
            35,
            0,
            0,
            16,
            0,
            0,
            0,
            0,
            0,
            0,
            0,
            116,
            101,
            120,
            116,
            117,
            114,
            101,
            79,
            117,
            116,
            108,
            105,
            110,
            101,
            83,
            104,
            97,
            112,
            101,
            52,
            50,
            58,
            115,
            116,
            97,
            110,
            100,
            95,
            48,
            48,
            48,
            95,
            51,
            48,
            50,
            95,
            112,
            52,
            0
          ]
        },
        "offset": 0
      },
      "SubData": {
        "BaseBuffer": {
          "type": "Buffer",
          "data": []
        },
        "offset": 0
      }
    },
    {
      "Children": [],
      "BlockType": "$CT0",
      "Unknown0C": 0,
      "Data": {
        "BaseBuffer": {
          "type": "Buffer",
          "data": []
        },
        "offset": 0
      },
      "SubData": {
        "BaseBuffer": {
          "type": "Buffer",
          "data": []
        },
        "offset": 0
      }
    }
  ],
  "UnknownShortList": [
    1,
    3,
    0,
    12,
    2,
    3,
    132,
    24,
    4,
    2,
    132,
    32,
    5,
    4
  ],
  "VertexDataSections": [
    {
      "StartOffset": 0,
      "SizePerVertex": 48
    }
  ],
  "BindBoneList": [],
  "UnknownFloatList": [
    {
      "Unknown00": -0.018545586615800858,
      "Unknown04": 0.8733330368995667,
      "Unknown08": 0
    },
    {
      "Unknown00": 0.9998958706855774,
      "Unknown04": 0.014432365074753761,
      "Unknown08": 0
    },
    {
      "Unknown00": -0.014432365074753761,
      "Unknown04": 0.9998958706855774,
      "Unknown08": 0
    },
    {
      "Unknown00": 0,
      "Unknown04": 0,
      "Unknown08": 1
    },
    {
      "Unknown00": 0.2897639870643616,
      "Unknown04": 0.8764011263847351,
      "Unknown08": 0
    }
  ],
  "BlockType": "$VTX",
  "Size": 137,
  "Unknown0C": 0,
  "MeshType": 516,
  "VertexCount": 1502,
  "UnknownShort0D": 1024,
  "UnknownByte0F": 1,
  "UnknownInt3219": 0,
  "BindBoneRoot": 65281,
  "Unknownstring": "map1",
  "Data": {
    "BaseBuffer": {
      "type": "Buffer",
      "data": [
        10,
        0,
        0,
        0,
        28,
        0,
        4,
        2,
        222,
        5,
        0,
        0,
        0,
        4,
        1,
        1,
        68,
        0,
        60,
        0,
        72,
        0,
        0,
        0,
        0,
        0,
        0,
        0,
        0,
        0,
        0,
        0,
        1,
        0,
        3,
        0,
        0,
        0,
        12,
        0,
        2,
        0,
        3,
        0,
        132,
        0,
        24,
        0,
        4,
        0,
        2,
        0,
        132,
        0,
        32,
        0,
        5,
        0,
        4,
        0,
        0,
        0,
        0,
        0,
        48,
        0,
        0,
        0,
        1,
        255,
        0,
        0,
        234,
        236,
        151,
        188,
        193,
        146,
        95,
        63,
        0,
        0,
        0,
        0,
        45,
        249,
        127,
        63,
        186,
        117,
        108,
        60,
        0,
        0,
        0,
        0,
        186,
        117,
        108,
        188,
        45,
        249,
        127,
        63,
        0,
        0,
        0,
        0,
        0,
        0,
        0,
        0,
        0,
        0,
        0,
        128,
        0,
        0,
        128,
        63,
        242,
        91,
        148,
        62,
        211,
        91,
        96,
        63,
        0,
        0,
        0,
        0,
        109,
        97,
        112,
        49,
        0
      ]
    },
    "offset": 137
  },
  "SubData": {
    "BaseBuffer": {
      "type": "Buffer",
      "data": [
        36,
        82,
        83,
        73,
        0,
        0,
        0,
        87,
        0,
        0,
        0,
        0,
        0,
        0,
        0,
        0,
        6,
        5,
        4,
        2,
        0,
        0,
        0,
        0,
        0,
        0,
        0,
        0,
        48,
        0,
        0,
        0,
        192,
        233,
        5,
        32,
        160,
        25,
        1,
        0,
        16,
        0,
        0,
        0,
        0,
        0,
        0,
        0,
        96,
        3,
        7,
        32,
        52,
        35,
        0,
        0,
        16,
        0,
        0,
        0,
        0,
        0,
        0,
        0,
        116,
        101,
        120,
        116,
        117,
        114,
        101,
        79,
        117,
        116,
        108,
        105,
        110,
        101,
        83,
        104,
        97,
        112,
        101,
        52,
        50,
        58,
        115,
        116,
        97,
        110,
        100,
        95,
        48,
        48,
        48,
        95,
        51,
        48,
        50,
        95,
        112,
        52,
        0,
        0,
        0,
        0,
        0,
        0,
        0,
        0,
        0,
        0,
        36,
        67,
        84,
        48,
        0,
        0,
        0,
        0,
        0,
        0,
        0,
        0,
        0,
        0,
        0,
        0
      ]
    },
    "offset": 128
  }
}